agent_jupyter_toolkit/__init__.py
agent_jupyter_toolkit/py.typed
agent_jupyter_toolkit/kernel/__init__.py
agent_jupyter_toolkit/kernel/hooks.py
agent_jupyter_toolkit/kernel/manager.py
agent_jupyter_toolkit/kernel/messages.py
agent_jupyter_toolkit/kernel/mimetypes.py
agent_jupyter_toolkit/kernel/serialization.py
agent_jupyter_toolkit/kernel/session.py
agent_jupyter_toolkit/kernel/transport.py
agent_jupyter_toolkit/kernel/types.py
agent_jupyter_toolkit/kernel/variable_ops.py
agent_jupyter_toolkit/kernel/variables.py
agent_jupyter_toolkit/kernel/transports/local.py
agent_jupyter_toolkit/kernel/transports/server.py
agent_jupyter_toolkit/notebook/__init__.py
agent_jupyter_toolkit/notebook/buffer.py
agent_jupyter_toolkit/notebook/cells.py
agent_jupyter_toolkit/notebook/config.py
agent_jupyter_toolkit/notebook/factory.py
agent_jupyter_toolkit/notebook/session.py
agent_jupyter_toolkit/notebook/transport.py
agent_jupyter_toolkit/notebook/types.py
agent_jupyter_toolkit/notebook/utils.py
agent_jupyter_toolkit/notebook/transports/__init__.py
agent_jupyter_toolkit/notebook/transports/contents.py
agent_jupyter_toolkit/notebook/transports/local_file.py
agent_jupyter_toolkit/notebook/transports/collab/__init__.py
agent_jupyter_toolkit/notebook/transports/collab/protocol.py
agent_jupyter_toolkit/notebook/transports/collab/transport.py
agent_jupyter_toolkit/notebook/transports/collab/yutils.py
agent_jupyter_toolkit/utils/__init__.py
agent_jupyter_toolkit/utils/execution.py
agent_jupyter_toolkit/utils/factories.py
agent_jupyter_toolkit/utils/outputs.py
agent_jupyter_toolkit/utils/packages.py
agent_jupyter_toolkit-0.2.14.dist-info/licenses/LICENSE
agent_jupyter_toolkit-0.2.14.dist-info/METADATA
agent_jupyter_toolkit-0.2.14.dist-info/WHEEL
agent_jupyter_toolkit-0.2.14.dist-info/top_level.txt
agent_jupyter_toolkit-0.2.14.dist-info/RECORD
