Metadata-Version: 2.4
Name: agent-jupyter-toolkit
Version: 0.2.14
Summary: A toolkit for building, managing, and extending Jupyter agent workflows, including kernel and notebook utilities.
Author-email: Roberto Rodriguez <9653181+Cyb3rWard0g@users.noreply.github.com>
License:                                  Apache License
Project-URL: Homepage, https://github.com/Cyb3rWard0g/agent-jupyter-toolkit
Project-URL: Repository, https://github.com/Cyb3rWard0g/agent-jupyter-toolkit
Project-URL: Issues, https://github.com/Cyb3rWard0g/agent-jupyter-toolkit/issues
Keywords: Jupyter,agents,kernels,notebooks,collaboration,data
Classifier: Programming Language :: Python :: 3
Classifier: Programming Language :: Python :: 3 :: Only
Classifier: Programming Language :: Python :: 3.11
Classifier: Programming Language :: Python :: 3.12
Classifier: Programming Language :: Python :: 3.13
Classifier: License :: OSI Approved :: Apache Software License
Classifier: Operating System :: OS Independent
Requires-Python: <3.14,>=3.11
License-File: LICENSE
Requires-Dist: jupyter-client>=8.8.0
Requires-Dist: nbformat>=5.10.4
Requires-Dist: pandas>=2.3.3
Requires-Dist: pyarrow>=23.0.0
Requires-Dist: aiohttp>=3.13.3
Requires-Dist: yarl>=1.22.0
Requires-Dist: pycrdt>=0.12.44
Requires-Dist: jupyter-core>=5.9.1
Requires-Dist: jupyter-ydoc>=3.3.4
Provides-Extra: dev
Requires-Dist: pytest>=9.0.2; extra == "dev"
Requires-Dist: pytest-asyncio>=1.3.0; extra == "dev"
Requires-Dist: anyio>=4.12.1; extra == "dev"
Requires-Dist: ipykernel; extra == "dev"
Requires-Dist: ruff>=0.14.13; extra == "dev"
Requires-Dist: black; extra == "dev"
Requires-Dist: build; extra == "dev"
Requires-Dist: twine; extra == "dev"
Requires-Dist: packaging; extra == "dev"
Requires-Dist: setuptools; extra == "dev"
Requires-Dist: setuptools_scm; extra == "dev"
Requires-Dist: wheel; extra == "dev"
Dynamic: license-file
